wechat_pyrobot/__init__.py
wechat_pyrobot/anti_revoke32.py
wechat_pyrobot/anti_revoke64.py
wechat_pyrobot/ctypes_json.py
wechat_pyrobot/get_contact_list.py
wechat_pyrobot/hooklog32.py
wechat_pyrobot/hooklog64.py
wechat_pyrobot/hookmsg32.py
wechat_pyrobot/hookmsg64.py
wechat_pyrobot/offset.py
wechat_pyrobot/plugin_class.py
wechat_pyrobot/sendmsg32.py
wechat_pyrobot/sendmsg64.py
wechat_pyrobot/msg_plugins/__init__.py
wechat_pyrobot/msg_plugins/download_emotion.py
wechat_pyrobot/msg_plugins/monitor_biz.py
wechat_pyrobot/msg_plugins/print_msg.py
wechat_pyrobot/other_plugins/__init__.py
wechat_pyrobot/other_plugins/http_api.py
wechat_pyrobot-1.3.0.dist-info/METADATA
wechat_pyrobot-1.3.0.dist-info/WHEEL
wechat_pyrobot-1.3.0.dist-info/licenses/LICENSE
wechat_pyrobot-1.3.0.dist-info/RECORD
