Metadata-Version: 2.3
Name: wechat_pyrobot
Version: 1.3.0
Summary: 注入Python到微信，并实现Python发送消息和接收消息
Project-URL: Homepage, https://github.com/kanadeblisst00/WeChat-PyRobot
Project-URL: Bug Tracker, https://github.com/kanadeblisst00/WeChat-PyRobot/issues
Author-email: kanadeblisst <kanade@blisst.cn>
License: Copyright (c) 2018 The Python Packaging Authority
License-File: LICENSE
Classifier: License :: OSI Approved :: MIT License
Classifier: Programming Language :: Python :: 3
Requires-Python: >=3.7
Requires-Dist: fastapi
Requires-Dist: keystone-engine
Requires-Dist: py-process-hooker>=0.3.0
Requires-Dist: pywin32
Requires-Dist: requests
Requires-Dist: uvicorn
